<?xml version="1.0" encoding="UTF-8"?>
<quiz>
<!-- question: 0  -->
  <question type="category">
    <category>
      <text>$course$/top/Défaut pour SB_LduBousquet/greenco</text>
    </category>
    <info format="html">
      <text></text>
    </info>
    <idnumber></idnumber>
  </question>

<!-- question: 2404636  -->
  <question type="multichoice">
    <name>
      <text>FR_Achat nouvel appareil</text>
    </name>
    <questiontext format="html">
      <text><![CDATA[<p dir="ltr" style="text-align: left;">Vous voulez regarder une émission / un programme et 2 options se présentent, laquelle choisir ?<br></p>]]></text>
    </questiontext>
    <generalfeedback format="html">
      <text></text>
    </generalfeedback>
    <defaultgrade>1.0000000</defaultgrade>
    <penalty>0.3333333</penalty>
    <hidden>0</hidden>
    <idnumber></idnumber>
    <single>true</single>
    <shuffleanswers>true</shuffleanswers>
    <answernumbering>none</answernumbering>
    <showstandardinstruction>0</showstandardinstruction>
    <correctfeedback format="html">
      <text>Votre réponse est correcte.</text>
    </correctfeedback>
    <partiallycorrectfeedback format="html">
      <text>Votre réponse est partiellement correcte.</text>
    </partiallycorrectfeedback>
    <incorrectfeedback format="html">
      <text>Votre réponse est incorrecte.</text>
    </incorrectfeedback>
    <shownumcorrect/>
    <answer fraction="100" format="html">
      <text><![CDATA[<p dir="ltr" style="text-align: left;">Télécharger l’émission pour ensuite la regarder<br></p>]]></text>
      <feedback format="html">
        <text></text>
      </feedback>
    </answer>
    <answer fraction="0" format="html">
      <text><![CDATA[<p dir="ltr" style="text-align: left;">Regarder le show en streaming<br></p>]]></text>
      <feedback format="html">
        <text></text>
      </feedback>
    </answer>
  </question>

<!-- question: 2404631  -->
  <question type="multichoice">
    <name>
      <text>FR_Achat ou location</text>
    </name>
    <questiontext format="html">
      <text><![CDATA[<p dir="ltr" style="text-align: left;">Il est plus éco-responsable de<br></p>]]></text>
    </questiontext>
    <generalfeedback format="html">
      <text></text>
    </generalfeedback>
    <defaultgrade>1.0000000</defaultgrade>
    <penalty>0.3333333</penalty>
    <hidden>0</hidden>
    <idnumber></idnumber>
    <single>true</single>
    <shuffleanswers>true</shuffleanswers>
    <answernumbering>none</answernumbering>
    <showstandardinstruction>0</showstandardinstruction>
    <correctfeedback format="html">
      <text>Your answer is correct.</text>
    </correctfeedback>
    <partiallycorrectfeedback format="html">
      <text>Your answer is partially correct.</text>
    </partiallycorrectfeedback>
    <incorrectfeedback format="html">
      <text>Your answer is incorrect.</text>
    </incorrectfeedback>
    <shownumcorrect/>
    <answer fraction="100" format="html">
      <text><![CDATA[<p dir="ltr" style="text-align: left;">Louer<br></p>]]></text>
      <feedback format="html">
        <text></text>
      </feedback>
    </answer>
    <answer fraction="0" format="html">
      <text><![CDATA[<p dir="ltr" style="text-align: left;">Acheter<br></p>]]></text>
      <feedback format="html">
        <text></text>
      </feedback>
    </answer>
  </question>

<!-- question: 2404623  -->
  <question type="multichoice">
    <name>
      <text>FR_Bilan environnemental</text>
    </name>
    <questiontext format="html">
      <text><![CDATA[<p dir="ltr" style="text-align: left;">Si vous possédez un ordinateur ou une tablette, comment pouvez vous améliorer son bilan environnemental ?<br></p>]]></text>
    </questiontext>
    <generalfeedback format="html">
      <text></text>
    </generalfeedback>
    <defaultgrade>1.0000000</defaultgrade>
    <penalty>0.3333333</penalty>
    <hidden>0</hidden>
    <idnumber></idnumber>
    <single>true</single>
    <shuffleanswers>true</shuffleanswers>
    <answernumbering>none</answernumbering>
    <showstandardinstruction>0</showstandardinstruction>
    <correctfeedback format="html">
      <text>Votre réponse est correcte.</text>
    </correctfeedback>
    <partiallycorrectfeedback format="html">
      <text>Votre réponse est partiellement correcte.</text>
    </partiallycorrectfeedback>
    <incorrectfeedback format="html">
      <text>Votre réponse est incorrecte.</text>
    </incorrectfeedback>
    <shownumcorrect/>
    <answer fraction="0" format="html">
      <text><![CDATA[<p dir="ltr" style="text-align: left;">Ne pas installer les mises à jour importantes<br></p>]]></text>
      <feedback format="html">
        <text></text>
      </feedback>
    </answer>
    <answer fraction="100" format="html">
      <text><![CDATA[<p dir="ltr" style="text-align: left;">Le garder le plus longtemps possible<br></p>]]></text>
      <feedback format="html">
        <text></text>
      </feedback>
    </answer>
    <answer fraction="0" format="html">
      <text><![CDATA[<p dir="ltr" style="text-align: left;">Éviter de le nettoyer le plus possible<br></p>]]></text>
      <feedback format="html">
        <text></text>
      </feedback>
    </answer>
    <answer fraction="0" format="html">
      <text><![CDATA[<p dir="ltr" style="text-align: left;">Acheter un nouvel appareil quand celui que vous avez devient trop lent<br></p>]]></text>
      <feedback format="html">
        <text></text>
      </feedback>
    </answer>
  </question>

<!-- question: 2404621  -->
  <question type="multichoice">
    <name>
      <text>FR_Consommation papier</text>
    </name>
    <questiontext format="html">
      <text><![CDATA[<p dir="ltr" style="text-align: left;">Combien de kg de papier consomme un salarié par an ?<br></p>]]></text>
    </questiontext>
    <generalfeedback format="html">
      <text></text>
    </generalfeedback>
    <defaultgrade>1.0000000</defaultgrade>
    <penalty>0.3333333</penalty>
    <hidden>0</hidden>
    <idnumber></idnumber>
    <single>true</single>
    <shuffleanswers>true</shuffleanswers>
    <answernumbering>none</answernumbering>
    <showstandardinstruction>0</showstandardinstruction>
    <correctfeedback format="html">
      <text>Votre réponse est correcte.</text>
    </correctfeedback>
    <partiallycorrectfeedback format="html">
      <text>Votre réponse est partiellement correcte.</text>
    </partiallycorrectfeedback>
    <incorrectfeedback format="html">
      <text>Votre réponse est incorrecte.</text>
    </incorrectfeedback>
    <shownumcorrect/>
    <answer fraction="100" format="html">
      <text><![CDATA[<p dir="ltr" style="text-align: left;">70 à 85kg<br></p>]]></text>
      <feedback format="html">
        <text></text>
      </feedback>
    </answer>
    <answer fraction="0" format="html">
      <text><![CDATA[<p dir="ltr" style="text-align: left;">3 à 5kg<br></p>]]></text>
      <feedback format="html">
        <text></text>
      </feedback>
    </answer>
    <answer fraction="0" format="html">
      <text><![CDATA[<p dir="ltr" style="text-align: left;">550 à 600kg<br></p>]]></text>
      <feedback format="html">
        <text></text>
      </feedback>
    </answer>
    <answer fraction="0" format="html">
      <text><![CDATA[<p dir="ltr" style="text-align: left;">20 à 30kg<br></p>]]></text>
      <feedback format="html">
        <text></text>
      </feedback>
    </answer>
  </question>

<!-- question: 2404620  -->
  <question type="multichoice">
    <name>
      <text>FR_Consommation reseau</text>
    </name>
    <questiontext format="html">
      <text><![CDATA[<p dir="ltr" style="text-align: left;">Lequel de ces reseaux consomme le moins ?<br></p>]]></text>
    </questiontext>
    <generalfeedback format="html">
      <text></text>
    </generalfeedback>
    <defaultgrade>1.0000000</defaultgrade>
    <penalty>0.3333333</penalty>
    <hidden>0</hidden>
    <idnumber></idnumber>
    <single>true</single>
    <shuffleanswers>true</shuffleanswers>
    <answernumbering>none</answernumbering>
    <showstandardinstruction>0</showstandardinstruction>
    <correctfeedback format="html">
      <text>Votre réponse est correcte.</text>
    </correctfeedback>
    <partiallycorrectfeedback format="html">
      <text>Votre réponse est partiellement correcte.</text>
    </partiallycorrectfeedback>
    <incorrectfeedback format="html">
      <text>Votre réponse est incorrecte.</text>
    </incorrectfeedback>
    <shownumcorrect/>
    <answer fraction="0" format="html">
      <text><![CDATA[<p dir="ltr" style="text-align: left;">Wifi<br></p>]]></text>
      <feedback format="html">
        <text></text>
      </feedback>
    </answer>
    <answer fraction="100" format="html">
      <text><![CDATA[<p dir="ltr" style="text-align: left;">Ethernet<br></p>]]></text>
      <feedback format="html">
        <text></text>
      </feedback>
    </answer>
    <answer fraction="0" format="html">
      <text><![CDATA[<p dir="ltr" style="text-align: left;">4G<br></p>]]></text>
      <feedback format="html">
        <text></text>
      </feedback>
    </answer>
  </question>

<!-- question: 2404622  -->
  <question type="multichoice">
    <name>
      <text>FR_Consommation reseau</text>
    </name>
    <questiontext format="html">
      <text><![CDATA[<p dir="ltr" style="text-align: left;">Il vaut mieux préférer le réseau Ethernet ou la 4G ?<br><br></p>]]></text>
    </questiontext>
    <generalfeedback format="html">
      <text></text>
    </generalfeedback>
    <defaultgrade>1.0000000</defaultgrade>
    <penalty>0.3333333</penalty>
    <hidden>0</hidden>
    <idnumber></idnumber>
    <single>true</single>
    <shuffleanswers>true</shuffleanswers>
    <answernumbering>none</answernumbering>
    <showstandardinstruction>0</showstandardinstruction>
    <correctfeedback format="html">
      <text>Votre réponse est correcte.</text>
    </correctfeedback>
    <partiallycorrectfeedback format="html">
      <text>Votre réponse est partiellement correcte.</text>
    </partiallycorrectfeedback>
    <incorrectfeedback format="html">
      <text>Votre réponse est incorrecte.</text>
    </incorrectfeedback>
    <shownumcorrect/>
    <answer fraction="100" format="html">
      <text><![CDATA[<p dir="ltr" style="text-align: left;">Ethernet<br></p>]]></text>
      <feedback format="html">
        <text></text>
      </feedback>
    </answer>
    <answer fraction="0" format="html">
      <text><![CDATA[<p dir="ltr" style="text-align: left;">4G<br><br></p>]]></text>
      <feedback format="html">
        <text></text>
      </feedback>
    </answer>
  </question>

<!-- question: 2404643  -->
  <question type="multichoice">
    <name>
      <text>FR_ICT</text>
    </name>
    <questiontext format="html">
      <text><![CDATA[<p dir="ltr" style="text-align: left;">Que signifie ICT&nbsp;?<br></p>]]></text>
    </questiontext>
    <generalfeedback format="html">
      <text><![CDATA[<p dir="ltr" style="text-align: left;">Donc les technologies qui permettent l’interaction avec le monde digital.<br></p>]]></text>
    </generalfeedback>
    <defaultgrade>1.0000000</defaultgrade>
    <penalty>0.3333333</penalty>
    <hidden>0</hidden>
    <idnumber></idnumber>
    <single>true</single>
    <shuffleanswers>true</shuffleanswers>
    <answernumbering>none</answernumbering>
    <showstandardinstruction>0</showstandardinstruction>
    <correctfeedback format="html">
      <text>Votre réponse est correcte.</text>
    </correctfeedback>
    <partiallycorrectfeedback format="html">
      <text>Votre réponse est partiellement correcte.</text>
    </partiallycorrectfeedback>
    <incorrectfeedback format="html">
      <text>Votre réponse est incorrecte.</text>
    </incorrectfeedback>
    <shownumcorrect/>
    <answer fraction="100" format="html">
      <text><![CDATA[<p dir="ltr" style="text-align: left;">Information and Communication Technology<br></p>]]></text>
      <feedback format="html">
        <text></text>
      </feedback>
    </answer>
    <answer fraction="0" format="html">
      <text><![CDATA[<p dir="ltr" style="text-align: left;">Informatic and Computing Technology<br></p>]]></text>
      <feedback format="html">
        <text></text>
      </feedback>
    </answer>
    <answer fraction="0" format="html">
      <text><![CDATA[<p dir="ltr" style="text-align: left;">Interesting and Calculable Technics<br></p>]]></text>
      <feedback format="html">
        <text></text>
      </feedback>
    </answer>
    <answer fraction="0" format="html">
      <text><![CDATA[<p dir="ltr" style="text-align: left;">Imaginary Conception of Templates<br></p>]]></text>
      <feedback format="html">
        <text></text>
      </feedback>
    </answer>
  </question>

<!-- question: 2404635  -->
  <question type="multichoice">
    <name>
      <text>FR_Navigateur</text>
    </name>
    <questiontext format="html">
      <text><![CDATA[<p dir="ltr" style="text-align: left;">Quels navigateurs utiliser ?<br></p>]]></text>
    </questiontext>
    <generalfeedback format="html">
      <text></text>
    </generalfeedback>
    <defaultgrade>1.0000000</defaultgrade>
    <penalty>0.3333333</penalty>
    <hidden>0</hidden>
    <idnumber></idnumber>
    <single>false</single>
    <shuffleanswers>true</shuffleanswers>
    <answernumbering>none</answernumbering>
    <showstandardinstruction>0</showstandardinstruction>
    <correctfeedback format="html">
      <text>Votre réponse est correcte.</text>
    </correctfeedback>
    <partiallycorrectfeedback format="html">
      <text>Votre réponse est partiellement correcte.</text>
    </partiallycorrectfeedback>
    <incorrectfeedback format="html">
      <text>Votre réponse est incorrecte.</text>
    </incorrectfeedback>
    <shownumcorrect/>
    <answer fraction="50" format="html">
      <text><![CDATA[<p dir="ltr" style="text-align: left;">Microsoft Edge<br></p>]]></text>
      <feedback format="html">
        <text></text>
      </feedback>
    </answer>
    <answer fraction="50" format="html">
      <text><![CDATA[<p dir="ltr" style="text-align: left;">Firefox<br></p>]]></text>
      <feedback format="html">
        <text></text>
      </feedback>
    </answer>
    <answer fraction="0" format="html">
      <text><![CDATA[<p dir="ltr" style="text-align: left;">Chrome<br></p>]]></text>
      <feedback format="html">
        <text></text>
      </feedback>
    </answer>
  </question>

<!-- question: 2404633  -->
  <question type="multichoice">
    <name>
      <text>FR_Plateforme streaming</text>
    </name>
    <questiontext format="html">
      <text><![CDATA[<p dir="ltr" style="text-align: left;">Quels plateforme pour écouter de la musique ?<br></p>]]></text>
    </questiontext>
    <generalfeedback format="html">
      <text><![CDATA[Si vous ne souhaitez qu écouter de la musique sur Youtube, pensez dans ce cas à utiliser un addon comme Audio Only for YouTube.<br>]]></text>
    </generalfeedback>
    <defaultgrade>1.0000000</defaultgrade>
    <penalty>0.3333333</penalty>
    <hidden>0</hidden>
    <idnumber></idnumber>
    <single>false</single>
    <shuffleanswers>true</shuffleanswers>
    <answernumbering>none</answernumbering>
    <showstandardinstruction>0</showstandardinstruction>
    <correctfeedback format="html">
      <text>Your answer is correct.</text>
    </correctfeedback>
    <partiallycorrectfeedback format="html">
      <text>Your answer is partially correct.</text>
    </partiallycorrectfeedback>
    <incorrectfeedback format="html">
      <text>Your answer is incorrect.</text>
    </incorrectfeedback>
    <shownumcorrect/>
    <answer fraction="0" format="html">
      <text><![CDATA[<p dir="ltr" style="text-align: left;">Youtube<br></p>]]></text>
      <feedback format="html">
        <text></text>
      </feedback>
    </answer>
    <answer fraction="50" format="html">
      <text><![CDATA[<p dir="ltr" style="text-align: left;">Spotify<br></p>]]></text>
      <feedback format="html">
        <text></text>
      </feedback>
    </answer>
    <answer fraction="50" format="html">
      <text><![CDATA[<p dir="ltr" style="text-align: left;">Soundcloud<br></p>]]></text>
      <feedback format="html">
        <text></text>
      </feedback>
    </answer>
    <answer fraction="0" format="html">
      <text><![CDATA[<p dir="ltr" style="text-align: left;">Dailymotion<br></p>]]></text>
      <feedback format="html">
        <text></text>
      </feedback>
    </answer>
  </question>

<!-- question: 2404641  -->
  <question type="multichoice">
    <name>
      <text>FR_Production CO2 numérique</text>
    </name>
    <questiontext format="html">
      <text><![CDATA[<p dir="ltr" style="text-align: left;">Quel pourcentage de la production globale de CO2 le numérique a-t-il produit en 2019&nbsp;?<br></p>]]></text>
    </questiontext>
    <generalfeedback format="html">
      <text></text>
    </generalfeedback>
    <defaultgrade>1.0000000</defaultgrade>
    <penalty>0.3333333</penalty>
    <hidden>0</hidden>
    <idnumber></idnumber>
    <single>true</single>
    <shuffleanswers>true</shuffleanswers>
    <answernumbering>none</answernumbering>
    <showstandardinstruction>0</showstandardinstruction>
    <correctfeedback format="html">
      <text>Votre réponse est correcte.</text>
    </correctfeedback>
    <partiallycorrectfeedback format="html">
      <text>Votre réponse est partiellement correcte.</text>
    </partiallycorrectfeedback>
    <incorrectfeedback format="html">
      <text>Votre réponse est incorrecte.</text>
    </incorrectfeedback>
    <shownumcorrect/>
    <answer fraction="100" format="html">
      <text><![CDATA[<p dir="ltr" style="text-align: left;">Environ 4%<br></p>]]></text>
      <feedback format="html">
        <text></text>
      </feedback>
    </answer>
    <answer fraction="0" format="html">
      <text><![CDATA[<p dir="ltr" style="text-align: left;">Environ 1%<br></p>]]></text>
      <feedback format="html">
        <text></text>
      </feedback>
    </answer>
    <answer fraction="0" format="html">
      <text><![CDATA[<p dir="ltr" style="text-align: left;">Environ 8%<br></p>]]></text>
      <feedback format="html">
        <text></text>
      </feedback>
    </answer>
    <answer fraction="0" format="html">
      <text><![CDATA[<p dir="ltr" style="text-align: left;">Moins d 1%<br></p>]]></text>
      <feedback format="html">
        <text></text>
      </feedback>
    </answer>
  </question>

<!-- question: 2404644  -->
  <question type="multichoice">
    <name>
      <text>FR_Recyclage</text>
    </name>
    <questiontext format="html">
      <text><![CDATA[<p dir="ltr" style="text-align: left;">Quelle part de déchet électronique est recyclée chaque année?<br></p>]]></text>
    </questiontext>
    <generalfeedback format="html">
      <text></text>
    </generalfeedback>
    <defaultgrade>1.0000000</defaultgrade>
    <penalty>0.3333333</penalty>
    <hidden>0</hidden>
    <idnumber></idnumber>
    <single>true</single>
    <shuffleanswers>true</shuffleanswers>
    <answernumbering>none</answernumbering>
    <showstandardinstruction>0</showstandardinstruction>
    <correctfeedback format="html">
      <text>Votre réponse est correcte.</text>
    </correctfeedback>
    <partiallycorrectfeedback format="html">
      <text>Votre réponse est partiellement correcte.</text>
    </partiallycorrectfeedback>
    <incorrectfeedback format="html">
      <text>Votre réponse est incorrecte.</text>
    </incorrectfeedback>
    <shownumcorrect/>
    <answer fraction="100" format="html">
      <text><![CDATA[<p dir="ltr" style="text-align: left;">10%<br></p>]]></text>
      <feedback format="html">
        <text></text>
      </feedback>
    </answer>
    <answer fraction="0" format="html">
      <text><![CDATA[<p dir="ltr" style="text-align: left;">50%<br></p>]]></text>
      <feedback format="html">
        <text></text>
      </feedback>
    </answer>
    <answer fraction="0" format="html">
      <text><![CDATA[<p dir="ltr" style="text-align: left;">90%<br></p>]]></text>
      <feedback format="html">
        <text></text>
      </feedback>
    </answer>
    <answer fraction="0" format="html">
      <text><![CDATA[<p dir="ltr" style="text-align: left;">25%<br></p>]]></text>
      <feedback format="html">
        <text></text>
      </feedback>
    </answer>
  </question>

<!-- question: 2404634  -->
  <question type="multichoice">
    <name>
      <text>FR_Spam</text>
    </name>
    <questiontext format="html">
      <text><![CDATA[<p dir="ltr" style="text-align: left;">Quelle part des mails sont des spams?<br></p>]]></text>
    </questiontext>
    <generalfeedback format="html">
      <text></text>
    </generalfeedback>
    <defaultgrade>1.0000000</defaultgrade>
    <penalty>0.3333333</penalty>
    <hidden>0</hidden>
    <idnumber></idnumber>
    <single>true</single>
    <shuffleanswers>true</shuffleanswers>
    <answernumbering>none</answernumbering>
    <showstandardinstruction>0</showstandardinstruction>
    <correctfeedback format="html">
      <text>Votre réponse est correcte.</text>
    </correctfeedback>
    <partiallycorrectfeedback format="html">
      <text>Votre réponse est partiellement correcte.</text>
    </partiallycorrectfeedback>
    <incorrectfeedback format="html">
      <text>Votre réponse est incorrecte.</text>
    </incorrectfeedback>
    <shownumcorrect/>
    <answer fraction="100" format="html">
      <text><![CDATA[<p dir="ltr" style="text-align: left;">90%<br></p>]]></text>
      <feedback format="html">
        <text></text>
      </feedback>
    </answer>
    <answer fraction="0" format="html">
      <text><![CDATA[<p dir="ltr" style="text-align: left;">50%<br></p>]]></text>
      <feedback format="html">
        <text></text>
      </feedback>
    </answer>
    <answer fraction="0" format="html">
      <text><![CDATA[<p dir="ltr" style="text-align: left;">25%<br></p>]]></text>
      <feedback format="html">
        <text></text>
      </feedback>
    </answer>
    <answer fraction="0" format="html">
      <text><![CDATA[<p dir="ltr" style="text-align: left;">95%<br></p>]]></text>
      <feedback format="html">
        <text></text>
      </feedback>
    </answer>
  </question>

<!-- question: 2404632  -->
  <question type="truefalse">
    <name>
      <text>FR_Consommation papier</text>
    </name>
    <questiontext format="html">
      <text><![CDATA[<p dir="ltr" style="text-align: left;">Le nombre de page d un document imprimé est le seul paramètre affectant l impact écologique de l impression.<br></p>]]></text>
    </questiontext>
    <generalfeedback format="html">
      <text><![CDATA[<p dir="ltr" style="text-align: left;">Il faut aussi faire attention à l’optimisation des mises en page des documents : suppression des pages blanches, de la taille des images, des espaces vides, réduction des interlignes, des marges, des aplats de couleurs etc.<br>On peut également faire l’impression en mode brouillon, avec plusieurs pages par feuille, recto verso, etc<br></p>]]></text>
    </generalfeedback>
    <defaultgrade>1.0000000</defaultgrade>
    <penalty>1.0000000</penalty>
    <hidden>0</hidden>
    <idnumber></idnumber>
    <answer fraction="0" format="moodle_auto_format">
      <text>true</text>
      <feedback format="html">
        <text></text>
      </feedback>
    </answer>
    <answer fraction="100" format="moodle_auto_format">
      <text>false</text>
      <feedback format="html">
        <text></text>
      </feedback>
    </answer>
  </question>

<!-- question: 2404624  -->
  <question type="truefalse">
    <name>
      <text>FR_Impact énergétique</text>
    </name>
    <questiontext format="html">
      <text><![CDATA[<p dir="ltr" style="text-align: left;">Pour limiter l impact énergétique d une batterie, il faut la laisser se décharger complètement avant de la recharger.<br></p>]]></text>
    </questiontext>
    <generalfeedback format="html">
      <text></text>
    </generalfeedback>
    <defaultgrade>1.0000000</defaultgrade>
    <penalty>1.0000000</penalty>
    <hidden>0</hidden>
    <idnumber></idnumber>
    <answer fraction="0" format="moodle_auto_format">
      <text>true</text>
      <feedback format="html">
        <text></text>
      </feedback>
    </answer>
    <answer fraction="100" format="moodle_auto_format">
      <text>false</text>
      <feedback format="html">
        <text></text>
      </feedback>
    </answer>
  </question>

<!-- question: 2404640  -->
  <question type="truefalse">
    <name>
      <text>FR_Production CO2 numérique</text>
    </name>
    <questiontext format="html">
      <text><![CDATA[<p dir="ltr" style="text-align: left;">Le numérique produit moins de CO2 que l’aviation.<br></p>]]></text>
    </questiontext>
    <generalfeedback format="html">
      <text><![CDATA[<p dir="ltr" style="text-align: left;">L’aviation produit environ 2&nbsp;% du CO2 global de 2019 contre 4&nbsp;% pour le numérique et 8&nbsp;% pour les véhicules légers.<br></p>]]></text>
    </generalfeedback>
    <defaultgrade>1.0000000</defaultgrade>
    <penalty>1.0000000</penalty>
    <hidden>0</hidden>
    <idnumber></idnumber>
    <answer fraction="0" format="moodle_auto_format">
      <text>true</text>
      <feedback format="html">
        <text></text>
      </feedback>
    </answer>
    <answer fraction="100" format="moodle_auto_format">
      <text>false</text>
      <feedback format="html">
        <text></text>
      </feedback>
    </answer>
  </question>

<!-- question: 0  -->
  <question type="category">
    <category>
      <text>$course$/top/Défaut pour SB_LduBousquet/greenco/energie</text>
    </category>
    <info format="html">
      <text></text>
    </info>
    <idnumber></idnumber>
  </question>

<!-- question: 2404642  -->
  <question type="multichoice">
    <name>
      <text>FR_Habitude écrans</text>
    </name>
    <questiontext format="html">
      <text><![CDATA[<p dir="ltr" style="text-align: left;">Quelle(s) habitude(s) adopter pour les écrans ?<br><br></p>]]></text>
    </questiontext>
    <generalfeedback format="html">
      <text></text>
    </generalfeedback>
    <defaultgrade>1.0000000</defaultgrade>
    <penalty>0.3333333</penalty>
    <hidden>0</hidden>
    <idnumber></idnumber>
    <single>false</single>
    <shuffleanswers>true</shuffleanswers>
    <answernumbering>none</answernumbering>
    <showstandardinstruction>0</showstandardinstruction>
    <correctfeedback format="html">
      <text>Votre réponse est correcte.</text>
    </correctfeedback>
    <partiallycorrectfeedback format="html">
      <text>Votre réponse est partiellement correcte.</text>
    </partiallycorrectfeedback>
    <incorrectfeedback format="html">
      <text>Votre réponse est incorrecte.</text>
    </incorrectfeedback>
    <shownumcorrect/>
    <answer fraction="25" format="html">
      <text><![CDATA[<p dir="ltr" style="text-align: left;">Les éteindre totalement hors utilisation<br></p>]]></text>
      <feedback format="html">
        <text></text>
      </feedback>
    </answer>
    <answer fraction="25" format="html">
      <text><![CDATA[<p dir="ltr" style="text-align: left;">Garder la luminosité au minimum<br></p>]]></text>
      <feedback format="html">
        <text></text>
      </feedback>
    </answer>
    <answer fraction="25" format="html">
      <text><![CDATA[<p dir="ltr" style="text-align: left;">Privilégier les moins gourmands en énergie lors de l’achat<br></p>]]></text>
      <feedback format="html">
        <text></text>
      </feedback>
    </answer>
    <answer fraction="25" format="html">
      <text><![CDATA[<p dir="ltr" style="text-align: left;">Utiliser les fonctionnalités d’économie d’énergie quand il y en a<br></p>]]></text>
      <feedback format="html">
        <text></text>
      </feedback>
    </answer>
    <answer fraction="0" format="html">
      <text><![CDATA[<p dir="ltr" style="text-align: left;">Acheter les plus grands écrans possibles<br></p>]]></text>
      <feedback format="html">
        <text></text>
      </feedback>
    </answer>
    <answer fraction="0" format="html">
      <text><![CDATA[<p dir="ltr" style="text-align: left;">Avoir plusieurs écrans pour réaliser des taches simples<br></p>]]></text>
      <feedback format="html">
        <text></text>
      </feedback>
    </answer>
    <answer fraction="0" format="html">
      <text><![CDATA[<p dir="ltr" style="text-align: left;">Acheter les dernières nouveautés dès leurs sorties<br></p>]]></text>
      <feedback format="html">
        <text></text>
      </feedback>
    </answer>
  </question>

<!-- question: 2404619  -->
  <question type="multichoice">
    <name>
      <text>FR_Visionnage d un contenu</text>
    </name>
    <questiontext format="html">
      <text><![CDATA[<p dir="ltr" style="text-align: left;">Il vaut mieux regarder la TV via<br></p>]]></text>
    </questiontext>
    <generalfeedback format="html">
      <text></text>
    </generalfeedback>
    <defaultgrade>1.0000000</defaultgrade>
    <penalty>0.3333333</penalty>
    <hidden>0</hidden>
    <idnumber></idnumber>
    <single>true</single>
    <shuffleanswers>true</shuffleanswers>
    <answernumbering>none</answernumbering>
    <showstandardinstruction>0</showstandardinstruction>
    <correctfeedback format="html">
      <text>Votre réponse est correcte.</text>
    </correctfeedback>
    <partiallycorrectfeedback format="html">
      <text>Votre réponse est partiellement correcte.</text>
    </partiallycorrectfeedback>
    <incorrectfeedback format="html">
      <text>Votre réponse est incorrecte.</text>
    </incorrectfeedback>
    <shownumcorrect/>
    <answer fraction="100" format="html">
      <text><![CDATA[<p dir="ltr" style="text-align: left;">La TNT<br></p>]]></text>
      <feedback format="html">
        <text></text>
      </feedback>
    </answer>
    <answer fraction="0" format="html">
      <text><![CDATA[<p dir="ltr" style="text-align: left;">L ADSL<br></p>]]></text>
      <feedback format="html">
        <text></text>
      </feedback>
    </answer>
  </question>

<!-- question: 2404638  -->
  <question type="truefalse">
    <name>
      <text>FR_Consommation énergétique téléphone</text>
    </name>
    <questiontext format="html">
      <text><![CDATA[<p dir="ltr" style="text-align: left;">La consommation énergétique d’un téléphone durant son cycle de vie est surtout dû à sa consommation électrique pure (rechargement)?<br></p>]]></text>
    </questiontext>
    <generalfeedback format="html">
      <text><![CDATA[<p dir="ltr" style="text-align: left;">La consommation indirecte d’énergie par l’utilisation de réseau et de service distant consomme environ 33 fois plus.<br></p>]]></text>
    </generalfeedback>
    <defaultgrade>1.0000000</defaultgrade>
    <penalty>1.0000000</penalty>
    <hidden>0</hidden>
    <idnumber></idnumber>
    <answer fraction="0" format="moodle_auto_format">
      <text>true</text>
      <feedback format="html">
        <text></text>
      </feedback>
    </answer>
    <answer fraction="100" format="moodle_auto_format">
      <text>false</text>
      <feedback format="html">
        <text></text>
      </feedback>
    </answer>
  </question>

<!-- question: 2404639  -->
  <question type="truefalse">
    <name>
      <text>FR_Production téléphone</text>
    </name>
    <questiontext format="html">
      <text><![CDATA[<p dir="ltr" style="text-align: left;">La production d’un téléphone pollue plus que son utilisation.<br></p>]]></text>
    </questiontext>
    <generalfeedback format="html">
      <text><![CDATA[<p dir="ltr" style="text-align: left;">Environ 400 fois plus.<br></p>]]></text>
    </generalfeedback>
    <defaultgrade>1.0000000</defaultgrade>
    <penalty>1.0000000</penalty>
    <hidden>0</hidden>
    <idnumber></idnumber>
    <answer fraction="100" format="moodle_auto_format">
      <text>true</text>
      <feedback format="html">
        <text></text>
      </feedback>
    </answer>
    <answer fraction="0" format="moodle_auto_format">
      <text>false</text>
      <feedback format="html">
        <text></text>
      </feedback>
    </answer>
  </question>

<!-- question: 2404637  -->
  <question type="truefalse">
    <name>
      <text>FR_Terminaux</text>
    </name>
    <questiontext format="html">
      <text><![CDATA[<p dir="ltr" style="text-align: left;">Les terminaux personnels représentent la majorité de l’impact du numérique<br></p>]]></text>
    </questiontext>
    <generalfeedback format="html">
      <text><![CDATA[<p dir="ltr" style="text-align: left;">Ils représentent 63 % du total et même dans le détail (particulièrement en coût en eau et ressources premières) face aux data center et infrastructure réseaux.<br></p>]]></text>
    </generalfeedback>
    <defaultgrade>1.0000000</defaultgrade>
    <penalty>1.0000000</penalty>
    <hidden>0</hidden>
    <idnumber></idnumber>
    <answer fraction="100" format="moodle_auto_format">
      <text>true</text>
      <feedback format="html">
        <text></text>
      </feedback>
    </answer>
    <answer fraction="0" format="moodle_auto_format">
      <text>false</text>
      <feedback format="html">
        <text></text>
      </feedback>
    </answer>
  </question>
</quiz>